README
setup.py
foursquare.pants.spindle.egg-info/PKG-INFO
foursquare.pants.spindle.egg-info/SOURCES.txt
foursquare.pants.spindle.egg-info/dependency_links.txt
foursquare.pants.spindle.egg-info/entry_points.txt
foursquare.pants.spindle.egg-info/namespace_packages.txt
foursquare.pants.spindle.egg-info/top_level.txt
foursquare/pants/spindle/__init__.py
foursquare/pants/spindle/spindle_codegen_task.py