Metadata-Version: 1.1
Name: foursquare.pants.spindle
Version: 0.0.1
Summary: Spindle Thrift-to-Scala code generation plugin for pants build system
Home-page: https://github.com/foursquare/pants-spindle
Author: Foursquare
Author-email: pants@foursquare.com
License: UNKNOWN
Download-URL: https://github.com/foursquare/pants-spindle/tags/v0.0.1
Keywords: pantsbuild,pantsbuild plugin,thrift,scala,codegen
Platform: UNKNOWN
